dfelf/__init__.py
dfelf/commons.py
dfelf/cvsfileelf.py
dfelf/datafileelf.py
dfelf/imagefileelf.py
dfelf/pdffileelf.py
dfelf/res/__init__.py
dfelf/res/Noto_Sans_SC/NotoSansSC-Regular.otf
dfelf/res/Noto_Sans_SC/OFL.txt
dfelf/res/Noto_Sans_SC/__init__.py
dfelf-0.2.1.dist-info/LICENSE
dfelf-0.2.1.dist-info/METADATA
dfelf-0.2.1.dist-info/WHEEL
dfelf-0.2.1.dist-info/top_level.txt
dfelf-0.2.1.dist-info/RECORD
