Metadata-Version: 2.1
Name: dfelf
Version: 0.2.1
Summary: Data File Elf
Home-page: https://github.com/KrixTam/dfelf
Author: Krix Tam
Author-email: krix.tam@qq.com
License: MIT
Project-URL: Bug Tracker, https://github.com/KrixTam/dfelf/issues
Classifier: Programming Language :: Python :: 3
Classifier: License :: OSI Approved :: MIT License
Classifier: Operating System :: OS Independent
Requires-Python: >=3.6
License-File: LICENSE
Requires-Dist: pymoment >=0.0.6
Requires-Dist: ni-config >=0.0.15
Requires-Dist: pandas >=2.2.2
Requires-Dist: Pillow >=10.3.0
Requires-Dist: qrcode >=7.4.2
Requires-Dist: opencv-python >=4.10.0.84
Requires-Dist: scikit-image >=0.23.2
Requires-Dist: PyMuPDF >=1.24.6
